[
    {
        "trialName": "IIT2021-01-Shiao-CSF1Ri: Reinvigorating TNBC Response to Immunotherapy With Combination Myeloid Inhibition and Radiation",
        "nctNumber": "NCT05491226",
        "statusVerifiedDate": "2024-03",
        "overallStatus": "RECRUITING",
        "startDate": "2023-11-17",
        "primaryCompletionDate": "2025-12-01",
        "completionDate": "2025-12-01",
        "studyFirstSubmitDate": "2022-08-04",
        "lastUpdateSubmitDate": "2024-03-21",
        "startDateType": "ACTUAL",
        "durationDays": 745,
        "daysUntilEnd": 482
    },
    {
        "trialName": "Phase 1/2 Study of PRO1184 in Patients With Locally Advanced and/or Metastatic Solid Tumors",
        "nctNumber": "NCT05579366",
        "statusVerifiedDate": "2024-07",
        "overallStatus": "RECRUITING",
        "startDate": "2022-12-07",
        "primaryCompletionDate": "2025-10",
        "completionDate": "2026-04",
        "studyFirstSubmitDate": "2022-10-04",
        "lastUpdateSubmitDate": "2024-07-23",
        "startDateType": "ACTUAL",
        "durationDays": 1211,
        "daysUntilEnd": 603
    },
    {
        "trialName": "A Phase II, Multicenter, Randomized, Double-Blind Study of Tobemstomig/RO7247669 Combined With Nab-Paclitaxel Compared With Pembrolizumab Combined With Nab-Paclitaxel in Participants With Previously Untreated, PD-L1-Positive, Locally-Advanced Unresectable or Metastatic Triple-Negative Breast Cancer",
        "nctNumber": "NCT05852691",
        "statusVerifiedDate": "2024-07",
        "overallStatus": "RECRUITING",
        "startDate": "2023-07-18",
        "primaryCompletionDate": "2025-12-01",
        "completionDate": "2026-02-27",
        "studyFirstSubmitDate": "2023-05-02",
        "lastUpdateSubmitDate": "2024-07-16",
        "startDateType": "ACTUAL",
        "durationDays": 955,
        "daysUntilEnd": 570
    },
    {
        "trialName": "A Phase 1-2 Dose-escalation and Expansion Study of ST316 in Subjects With Selected Advanced Unresectable and Metastatic Solid Tumors",
        "nctNumber": "NCT05848739",
        "statusVerifiedDate": "2024-06",
        "overallStatus": "RECRUITING",
        "startDate": "2023-06-05",
        "primaryCompletionDate": "2026-05-31",
        "completionDate": "2027-05-31",
        "studyFirstSubmitDate": "2023-03-21",
        "lastUpdateSubmitDate": "2024-06-03",
        "startDateType": "ACTUAL",
        "durationDays": 1456,
        "daysUntilEnd": 1028
    },
    {
        "trialName": "A Phase 2, Multicenter, Open-Label Basket Study of Navicixizumab Monotherapy or in Combination With Paclitaxel or Irinotecan in Patients With Select Advanced Solid Tumors",
        "nctNumber": "NCT05453825",
        "statusVerifiedDate": "2023-01",
        "overallStatus": "RECRUITING",
        "startDate": "2022-08-05",
        "primaryCompletionDate": "2024-04-15",
        "completionDate": "2024-12-15",
        "studyFirstSubmitDate": "2022-07-07",
        "lastUpdateSubmitDate": "2023-01-30",
        "startDateType": "ACTUAL",
        "durationDays": 863,
        "daysUntilEnd": 131
    },
    {
        "trialName": "A Phase 1a, Dose Escalation, Safety and Tolerability Study of NX-1607, a Casitas B-lineage Lymphoma Proto-oncogene (CBL-B) Inhibitor, in Adults With Advanced Malignancies, With Phase 1b Expansion in Select Tumor Types",
        "nctNumber": "NCT05107674",
        "statusVerifiedDate": "2024-06",
        "overallStatus": "RECRUITING",
        "startDate": "2021-09-29",
        "primaryCompletionDate": "2024-08-31",
        "completionDate": "2026-02-28",
        "studyFirstSubmitDate": "2021-09-22",
        "lastUpdateSubmitDate": "2024-06-14",
        "startDateType": "ACTUAL",
        "durationDays": 1613,
        "daysUntilEnd": 571
    },
    {
        "trialName": "A Phase 1/2 Study of BMS-986449 Alone and in Combination With Nivolumab in Participants With Advanced Solid Tumors",
        "nctNumber": "NCT05888831",
        "statusVerifiedDate": "2024-07",
        "overallStatus": "RECRUITING",
        "startDate": "2023-06-06",
        "primaryCompletionDate": "2025-05-21",
        "completionDate": "2027-07-01",
        "studyFirstSubmitDate": "2023-05-25",
        "lastUpdateSubmitDate": "2024-07-31",
        "startDateType": "ACTUAL",
        "durationDays": 1486,
        "daysUntilEnd": 1059
    },
    {
        "trialName": "A Phase 1 Dose-Escalation and Expansion Study of Intratumorally Administered ONM-501 Alone and in Combination With Cemiplimab in Patients With Advanced Solid Tumors and Lymphomas",
        "nctNumber": "NCT06022029",
        "statusVerifiedDate": "2024-07",
        "overallStatus": "RECRUITING",
        "startDate": "2023-10-13",
        "primaryCompletionDate": "2026-04-30",
        "completionDate": "2026-08-29",
        "studyFirstSubmitDate": "2023-08-15",
        "lastUpdateSubmitDate": "2024-07-30",
        "startDateType": "ACTUAL",
        "durationDays": 1051,
        "daysUntilEnd": 753
    },
    {
        "trialName": "A Tissue Collection Study in Patients Who Respond to Immune Checkpoint Inhibitors to Identify Targets of Tumor-Reactive T Cells.",
        "nctNumber": "NCT05230186",
        "statusVerifiedDate": "2022-01",
        "overallStatus": "RECRUITING",
        "startDate": "2021-02-26",
        "primaryCompletionDate": "2024-12-23",
        "completionDate": "2024-12-23",
        "studyFirstSubmitDate": "2022-01-27",
        "lastUpdateSubmitDate": "2022-02-08",
        "startDateType": "ACTUAL",
        "durationDays": 1396,
        "daysUntilEnd": 139
    },
    {
        "trialName": "A Single Arm Phase 2 Study of Peri-Operative Immune Checkpoint Inhibition and Cryoablation in Women With Hormone Receptor-Negative, HER2-Negative Early Stage/Resectable Breast Cancer.",
        "nctNumber": "NCT03546686",
        "statusVerifiedDate": "2024-07",
        "overallStatus": "RECRUITING",
        "startDate": "2019-11-12",
        "primaryCompletionDate": "2026-06",
        "completionDate": "2028-06",
        "studyFirstSubmitDate": "2018-05-23",
        "lastUpdateSubmitDate": "2024-07-23",
        "startDateType": "ACTUAL",
        "durationDays": 3124,
        "daysUntilEnd": 1395
    },
    {
        "trialName": "A Phase 1 Study of NM32-2668 (Anti-ROR1/CD3/Anti-HSA Tri-Specific Antibody) in Adult Patients With Selected Advanced Solid Tumors",
        "nctNumber": "NCT06299163",
        "statusVerifiedDate": "2024-03",
        "overallStatus": "RECRUITING",
        "startDate": "2024-05-01",
        "primaryCompletionDate": "2027-12-31",
        "completionDate": "2027-12-31",
        "studyFirstSubmitDate": "2024-02-26",
        "lastUpdateSubmitDate": "2024-05-07",
        "startDateType": "ACTUAL",
        "durationDays": 1339,
        "daysUntilEnd": 1242
    },
    {
        "trialName": "A Phase I/II Study Evaluating the Safety and Efficacy of Ivermectin in Combination With Balstilimab in Patients With Metastatic Triple Negative Breast Cancer With Expansion Cohort in PD-L1 Negative TNBC",
        "nctNumber": "NCT05318469",
        "statusVerifiedDate": "2024-04",
        "overallStatus": "RECRUITING",
        "startDate": "2023-10-13",
        "primaryCompletionDate": "2026-10",
        "completionDate": "2026-10",
        "studyFirstSubmitDate": "2022-04-01",
        "lastUpdateSubmitDate": "2024-04-01",
        "startDateType": "ACTUAL",
        "durationDays": 1084,
        "daysUntilEnd": 786
    },
    {
        "trialName": "Shorter Anthracycline-Free Chemo Immunotherapy Adapted to Pathological Response in Early Triple Negative Breast Cancer (SCARLET), A Randomized Phase III Study",
        "nctNumber": "NCT05929768",
        "statusVerifiedDate": "2023-10",
        "overallStatus": "RECRUITING",
        "startDate": "2023-09-15",
        "primaryCompletionDate": "2033-03-31",
        "completionDate": "2033-04",
        "studyFirstSubmitDate": "2023-06-01",
        "lastUpdateSubmitDate": "2023-10-24",
        "startDateType": "ACTUAL",
        "durationDays": 3486,
        "daysUntilEnd": 3160
    },
    {
        "trialName": "A Phase 1 Study of HMBD-002-V4C26 (HMBD-002), a Monoclonal Antibody Targeting VISTA, as Monotherapy and Combined With Pembrolizumab, in Patients With Advanced Solid Malignancies",
        "nctNumber": "NCT05082610",
        "statusVerifiedDate": "2023-08",
        "overallStatus": "RECRUITING",
        "startDate": "2022-01-01",
        "primaryCompletionDate": "2024-10",
        "completionDate": "2025-01",
        "studyFirstSubmitDate": "2021-09-21",
        "lastUpdateSubmitDate": "2023-08-07",
        "startDateType": "ACTUAL",
        "durationDays": 1096,
        "daysUntilEnd": 148
    },
    {
        "trialName": "A Phase 1, First-in-Human, Dose-Finding and Expansion Study to Evaluate the Safety, Tolerability, Pharmacokinetics, and Activity of XmAb\u00ae808 in Combination With Pembrolizumab in Selected Advanced Solid Tumors",
        "nctNumber": "NCT05585034",
        "statusVerifiedDate": "2024-04",
        "overallStatus": "RECRUITING",
        "startDate": "2022-12-14",
        "primaryCompletionDate": "2027-12",
        "completionDate": "2027-12",
        "studyFirstSubmitDate": "2022-10-11",
        "lastUpdateSubmitDate": "2024-04-24",
        "startDateType": "ACTUAL",
        "durationDays": 1813,
        "daysUntilEnd": 1212
    },
    {
        "trialName": "A Dose Finding Phase 1 of Sarilumab Plus Capecitabine in HER2/Neu-Negative Metastatic Breast Cancer and a Single-arm, Historically-controlled Phase 2 Study of Sarilumab Plus Capecitabine in Stage I-III Triple Negative Breast Cancer With High-Risk Residual Disease (EMPOWER)",
        "nctNumber": "NCT04333706",
        "statusVerifiedDate": "2024-01",
        "overallStatus": "RECRUITING",
        "startDate": "2020-09-26",
        "primaryCompletionDate": "2025-11-03",
        "completionDate": "2026-11-03",
        "studyFirstSubmitDate": "2020-04-01",
        "lastUpdateSubmitDate": "2024-01-16",
        "startDateType": "ACTUAL",
        "durationDays": 2229,
        "daysUntilEnd": 819
    },
    {
        "trialName": "An Open-label, Multicenter, Multicohort, Phase 2 Study to Evaluate Enfortumab Vedotin in Subjects With Locally Advanced or Metastatic Malignant Solid Tumors (EV-202)",
        "nctNumber": "NCT04225117",
        "statusVerifiedDate": "2024-07",
        "overallStatus": "RECRUITING",
        "startDate": "2020-03-09",
        "primaryCompletionDate": "2026-09-30",
        "completionDate": "2026-09-30",
        "studyFirstSubmitDate": "2020-01-09",
        "lastUpdateSubmitDate": "2024-07-19",
        "startDateType": "ACTUAL",
        "durationDays": 2396,
        "daysUntilEnd": 785
    },
    {
        "trialName": "Increasing Access to Genetic Testing in Underserved Patients Using a Multilingual Conversational Agent",
        "nctNumber": "NCT06422455",
        "statusVerifiedDate": "2024-05",
        "overallStatus": "NOT_YET_RECRUITING",
        "startDate": "2024-07-01",
        "primaryCompletionDate": "2026-07-01",
        "completionDate": "2027-07-01",
        "studyFirstSubmitDate": "2024-05-15",
        "lastUpdateSubmitDate": "2024-05-20",
        "startDateType": "ESTIMATED",
        "durationDays": 1095,
        "daysUntilEnd": 1059
    },
    {
        "trialName": "A Dose-Escalation and Expansion Study of the Safety and Pharmacokinetics of XB002 as Single-Agent and Combination Therapy in Subjects With Inoperable Locally Advanced or Metastatic Solid Tumors",
        "nctNumber": "NCT04925284",
        "statusVerifiedDate": "2024-02",
        "overallStatus": "RECRUITING",
        "startDate": "2021-06-07",
        "primaryCompletionDate": "2024-06-07",
        "completionDate": "2024-10-07",
        "studyFirstSubmitDate": "2021-05-27",
        "lastUpdateSubmitDate": "2024-05-01",
        "startDateType": "ACTUAL",
        "durationDays": 1218,
        "daysUntilEnd": 62
    },
    {
        "trialName": "Phase 1/2 Safety and Efficacy Study of NUV-868 as Monotherapy and in Combination With Olaparib or Enzalutamide in Adult Patients With Advanced Solid Tumors",
        "nctNumber": "NCT05252390",
        "statusVerifiedDate": "2024-05",
        "overallStatus": "RECRUITING",
        "startDate": "2022-03-29",
        "primaryCompletionDate": "2026-06",
        "completionDate": "2026-11",
        "studyFirstSubmitDate": "2022-01-28",
        "lastUpdateSubmitDate": "2024-07-23",
        "startDateType": "ACTUAL",
        "durationDays": 1678,
        "daysUntilEnd": 817
    },
    {
        "trialName": "A Phase III, Open-label, Randomised Study of Neoadjuvant Datopotamab Deruxtecan (Dato-DXd) Plus Durvalumab Followed by Adjuvant Durvalumab With or Without Chemotherapy Versus Neoadjuvant Pembrolizumab Plus Chemotherapy Followed by Adjuvant Pembrolizumab With or Without Chemotherapy for the Treatment of Adult Patients With Previously Untreated Triple-Negative or Hormone Receptor-low/HER2-negative Breast Cancer (D926QC00001; TROPION-Breast04)",
        "nctNumber": "NCT06112379",
        "statusVerifiedDate": "2024-07",
        "overallStatus": "RECRUITING",
        "startDate": "2023-11-14",
        "primaryCompletionDate": "2028-03-29",
        "completionDate": "2030-08-28",
        "studyFirstSubmitDate": "2023-10-12",
        "lastUpdateSubmitDate": "2024-07-10",
        "startDateType": "ACTUAL",
        "durationDays": 2479,
        "daysUntilEnd": 2213
    },
    {
        "trialName": "I-SPY Trial (Investigation of Serial Studies to Predict Your Therapeutic Response With Imaging And moLecular Analysis 2)",
        "nctNumber": "NCT01042379",
        "statusVerifiedDate": "2024-04",
        "overallStatus": "RECRUITING",
        "startDate": "2010-03-01",
        "primaryCompletionDate": "2030-12",
        "completionDate": "2031-12",
        "studyFirstSubmitDate": "2009-12-31",
        "lastUpdateSubmitDate": "2024-04-22",
        "startDateType": "ACTUAL",
        "durationDays": 7945,
        "daysUntilEnd": 2673
    },
    {
        "trialName": "A Phase 3 Open-label, Randomised Study of Datopotamab Deruxtecan (DatoDXd) With or Without Durvalumab Versus Investigator's Choice of Therapy in Patients With Stage I-III Triple-negative Breast Cancer Who Have Residual Invasive Disease in the Breast and/or Axillary Lymph Nodes at Surgical Resection Following Neoadjuvant Systemic Therapy (TROPION-Breast03)",
        "nctNumber": "NCT05629585",
        "statusVerifiedDate": "2024-07",
        "overallStatus": "RECRUITING",
        "startDate": "2022-11-28",
        "primaryCompletionDate": "2027-09-20",
        "completionDate": "2030-03-27",
        "studyFirstSubmitDate": "2022-11-04",
        "lastUpdateSubmitDate": "2024-07-22",
        "startDateType": "ACTUAL",
        "durationDays": 2676,
        "daysUntilEnd": 2059
    },
    {
        "trialName": "Phase 1, Two-part, Multicenter, Open-label, Multiple Dose, First-in-human Study of DS-1062a in Subjects With Advanced Solid Tumors (TROPION-PanTumor01)",
        "nctNumber": "NCT03401385",
        "statusVerifiedDate": "2023-06",
        "overallStatus": "RECRUITING",
        "startDate": "2018-01-31",
        "primaryCompletionDate": "2025-01-01",
        "completionDate": "2025-01-01",
        "studyFirstSubmitDate": "2018-01-09",
        "lastUpdateSubmitDate": "2023-06-15",
        "startDateType": "ACTUAL",
        "durationDays": 2527,
        "daysUntilEnd": 148
    },
    {
        "trialName": "OptimICE-PCR: De-Escalation of Therapy in Early-Stage TNBC Patients Who Achieve pCR After Neoadjuvant Chemotherapy With Checkpoint Inhibitor Therapy",
        "nctNumber": "NCT05812807",
        "statusVerifiedDate": "2024-08",
        "overallStatus": "RECRUITING",
        "startDate": "2023-05-10",
        "primaryCompletionDate": "2033-05-31",
        "completionDate": "2033-05-31",
        "studyFirstSubmitDate": "2023-03-23",
        "lastUpdateSubmitDate": "2024-08-01",
        "startDateType": "ACTUAL",
        "durationDays": 3674,
        "daysUntilEnd": 3220
    },
    {
        "trialName": "A Phase 1/2 Safety and Efficacy Dose Escalation / Dose Expansion Study of a CAB-ROR2-ADC, Alone and in Combination With a PD-1 Inhibitor, in Patients With Advanced Solid Tumors (Ph1) and Melanoma and NSCLC Patients (Ph2)",
        "nctNumber": "NCT03504488",
        "statusVerifiedDate": "2024-01",
        "overallStatus": "RECRUITING",
        "startDate": "2018-06-27",
        "primaryCompletionDate": "2025-12-30",
        "completionDate": "2025-12-30",
        "studyFirstSubmitDate": "2018-04-12",
        "lastUpdateSubmitDate": "2024-01-29",
        "startDateType": "ACTUAL",
        "durationDays": 2743,
        "daysUntilEnd": 511
    },
    {
        "trialName": "Phase Ib Clinical Trial of Autologous Anti-NY-ESO-1 TCR-Engineered T Cells in Patients With Relapsed/Refractory Locally Advanced or Metastatic NY-ESO-1-Expressing Triple Negative Breast Cancer",
        "nctNumber": "NCT05989828",
        "statusVerifiedDate": "2024-05",
        "overallStatus": "NOT_YET_RECRUITING",
        "startDate": "2024-08-01",
        "primaryCompletionDate": "2026-08-01",
        "completionDate": "2027-08-01",
        "studyFirstSubmitDate": "2023-06-27",
        "lastUpdateSubmitDate": "2024-05-22",
        "startDateType": "ESTIMATED",
        "durationDays": 1095,
        "daysUntilEnd": 1090
    },
    {
        "trialName": "A Phase 1/2 Study of BMS-986340 as Monotherapy and in Combination With Nivolumab or Docetaxel in Participants With Advanced Solid Tumors",
        "nctNumber": "NCT04895709",
        "statusVerifiedDate": "2024-07",
        "overallStatus": "RECRUITING",
        "startDate": "2021-05-27",
        "primaryCompletionDate": "2025-12-31",
        "completionDate": "2026-12-31",
        "studyFirstSubmitDate": "2021-05-19",
        "lastUpdateSubmitDate": "2024-08-02",
        "startDateType": "ACTUAL",
        "durationDays": 2044,
        "daysUntilEnd": 877
    },
    {
        "trialName": "A Phase 2a, Single-arm, Multi-center, Open-label Study of Neoadjuvant INBRX-106 (Hexavalent OX40 Agonist) in Combination With Pembrolizumab as a Chemotherapy-sparing Regimen for Stage II TNBC Patients",
        "nctNumber": "NCT06353997",
        "statusVerifiedDate": "2024-07",
        "overallStatus": "NOT_YET_RECRUITING",
        "startDate": "2024-08",
        "primaryCompletionDate": "2026-06",
        "completionDate": "2029-06",
        "studyFirstSubmitDate": "2024-03-26",
        "lastUpdateSubmitDate": "2024-07-25",
        "startDateType": "ESTIMATED",
        "durationDays": 1765,
        "daysUntilEnd": 1760
    },
    {
        "trialName": "A Randomized, Open-label, Phase 3 Study of Adjuvant Sacituzumab Govitecan and Pembrolizumab Versus Treatment of Physician's Choice in Patients With Triple Negative Breast Cancer Who Have Residual Invasive Disease After Surgery and Neoadjuvant Therapy",
        "nctNumber": "NCT05633654",
        "statusVerifiedDate": "2024-06",
        "overallStatus": "RECRUITING",
        "startDate": "2022-12-12",
        "primaryCompletionDate": "2027-06",
        "completionDate": "2031-08",
        "studyFirstSubmitDate": "2022-11-21",
        "lastUpdateSubmitDate": "2024-06-24",
        "startDateType": "ACTUAL",
        "durationDays": 3154,
        "daysUntilEnd": 2551
    }
]